bloodhound/__init__.py
bloodhound/__main__.py
bloodhound/ad/__init__.py
bloodhound/ad/authentication.py
bloodhound/ad/computer.py
bloodhound/ad/domain.py
bloodhound/ad/dumpntlm.py
bloodhound/ad/structures.py
bloodhound/ad/trusts.py
bloodhound/ad/utils.py
bloodhound/enumeration/__init__.py
bloodhound/enumeration/acls.py
bloodhound/enumeration/computers.py
bloodhound/enumeration/domains.py
bloodhound/enumeration/memberships.py
bloodhound/enumeration/objectresolver.py
bloodhound/enumeration/outputworker.py
bloodhound/lib/__init__.py
bloodhound/lib/cstruct.py
bloodhound-1.7.2.dist-info/LICENSE
bloodhound-1.7.2.dist-info/METADATA
bloodhound-1.7.2.dist-info/WHEEL
bloodhound-1.7.2.dist-info/entry_points.txt
bloodhound-1.7.2.dist-info/top_level.txt
bloodhound-1.7.2.dist-info/RECORD
