Metadata-Version: 1.2
Name: bloodhound
Version: 1.7.2
Summary: Python based ingestor for BloodHound
Home-page: https://github.com/dirkjanm/bloodhound.py
Author: Dirk-jan Mollema, Edwin van Vliet, Matthijs Gielen
Author-email: dirkjan@dirkjanm.io, edwin.vanvliet@fox-it.com, matthijs.gielen@fox-it.com
Maintainer: Dirk-jan Mollema
Maintainer-email: dirkjan@dirkjanm.io
License: MIT
Platform: UNKNOWN
Classifier: Intended Audience :: Information Technology
Classifier: License :: OSI Approved :: MIT License
Classifier: Programming Language :: Python :: 3.6
Classifier: Programming Language :: Python :: 3.7
Classifier: Programming Language :: Python :: 3.8
Classifier: Programming Language :: Python :: 3.9
Classifier: Programming Language :: Python :: 3.10
Classifier: Programming Language :: Python :: 3.11
